Workbook

Sheet FLOW_Sensitivity
A1: Key Parameters for LCOE Sensitivity Analysis | B1: min LCOE | C1: base LCOE | D1: max LCOE | E1: min value | F1: base value | G1: max value | H1: color
A2: CapEx ($/kW) | B2: =($E$2*'Fixed Charge Rates'!$C$19+$F$3)/($F$4/100*8760/1000) -> 146.20621 | C2: =($F$2*'Fixed Charge Rates'!$C$19+$F$3)/($F$4/100*8766/1000) -> 182.68797 | D2: =($G$2*'Fixed Charge Rates'!$C$19+$F$3)/($F$4/100*8760/1000) -> 219.41998 | E2: =F2*0.75 -> 6179.3161 | F2: 8239.0881 | G2: =F2*1.25 -> 10298.86 | H2: midnightblue
A3: OpEx ($/kW/year) | B3: =($F$2*'Fixed Charge Rates'!$C$19+$E$3)/($F$4/100*8760/1000) -> 164.62031 | C3: =($F$2*'Fixed Charge Rates'!$C$19+$F$3)/($F$4/100*8766/1000) -> 182.68797 | D3: =($F$2*'Fixed Charge Rates'!$C$19+$G$3)/($F$4/100*8760/1000) -> 201.00588 | E3: =F3*0.5 -> 72.283806 | F3: 144.56761 | G3: =F3*1.5 -> 216.85142 | H3: silver
A4: Net Capacity Factor (%) | B4: =($F$2*'Fixed Charge Rates'!$C$19+$F$3)/($E$4/100*8760/1000) -> 150.7587 | C4: =($F$2*'Fixed Charge Rates'!$C$19+$F$3)/($F$4/100*8766/1000) -> 182.68797 | D4: =($F$2*'Fixed Charge Rates'!$C$19+$F$3)/($G$4/100*8760/1000) -> 236.90653 | E4: 55 | F4: =0.453563159736764*100 -> 45.356316 | G4: 35 | H4: deepskyblue
A5: Discount Rate (nominal) [%] | B5: =($F$2*'Fixed Charge Rates'!$D$19+$F$3)/($F$4/100*8760/1000) -> 156.578 | C5: =($F$2*'Fixed Charge Rates'!$C$19+$F$3)/($F$4/100*8766/1000) -> 182.68797 | D5: =($F$2*'Fixed Charge Rates'!$E$19+$F$3)/($F$4/100*8760/1000) -> 211.75957 | E5: =F5*0.75 -> 5.2548037 | F5: ='Fixed Charge Rates'!C10*100 -> 7.006405 | G5: =F5*1.25 -> 8.7580062 | H5: yellowgreen
A6: Project Design Life (Years) | B6: =($F$2*'Fixed Charge Rates'!$G$19+$F$3)/($F$4/100*8760/1000) -> 160.37231 | C6: =($F$2*'Fixed Charge Rates'!$C$19+$F$3)/($F$4/100*8766/1000) -> 182.68797 | D6: =($F$2*'Fixed Charge Rates'!$F$19+$F$3)/($F$4/100*8760/1000) -> 239.27962 | E6: 35 | F6: 25 | G6: 15 | H6: darkorange

Sheet Fixed Charge Rates
C1: baseline | D1: min WACC | E1: max WACC | F1: min lifetime | G1: max lifetime
A2: Project design life | B2: years | C2: 25 | D2: 25 | E2: 25 | F2: 15 | G2: 35
A3: Tax Rate (combined state and federal) | B3: % | C3: =SUM(C4,C5) -> 0.257 | D3: =SUM(D4,D5) -> 0.257 | E3: =SUM(E4,E5) -> 0.257 | F3: =SUM(F4,F5) -> 0.257 | G3: =SUM(G4,G5) -> 0.257
A4: Federal | B4: % | C4: 0.21 | D4: 0.21 | E4: 0.21 | F4: 0.21 | G4: 0.21 | I4: Mid-year Convention
A5: State | B5: % | C5: 0.047 | D5: 0.047 | E5: 0.047 | F5: 0.047 | G5: 0.047 | I5: Year | J5: Check | K5: NPV Depreciation | L5: 1 | M5: 2 | N5: 3 | O5: 4 | P5: 5 | Q5: 6 | R5: 7 | S5: 8 | T5: 9 | U5: 10 | V5: 11 | W5: 12 | X5: 13 | Y5: 14 | Z5: 15 | AA5: 16 | AB5: 17 | AC5: 18 | AD5: 19 | AE5: 20 | AF5: 21
A6: Inflation rate | B6: % | C6: 0.025 | D6: 0.025 | E6: 0.025 | F6: 0.025 | G6: 0.025 | I6: 5 year MACRS | J6: 1 | K6: =NPV(L82,$L$6:$Q$6)*L86 -> 0 | L6: 0.2 | M6: 0.32 | N6: 0.192 | O6: 0.1152 | P6: 0.1152 | Q6: 0.0576
A7: Debt fraction | B7: % | C7: 0.6161 | D7: 0.6161 | E7: 0.6161 | F7: 0.6161 | G7: 0.6161
A8: Debt interest rate (nominal) | B8: % | C8: 0.065 | D8: 0.065 | E8: 0.065 | F8: 0.065 | G8: 0.065
A9: Return on equity (nominal) | B9: % | C9: 0.105 | D9: 0.105 | E9: 0.105 | F9: 0.105 | G9: 0.105
A10: WACC (nominal; after-tax) | B10: % | C10: =C7*(C8*(1-C3))+(1-C7)*C9 -> 0.07006405 | D10: =FLOW_Sensitivity!E5/100 -> 0.052548037 | E10: =FLOW_Sensitivity!G5/100 -> 0.087580062 | F10: =F7*(F8*(1-F3))+(1-F7)*F9 -> 0.07006405 | G10: =G7*(G8*(1-G3))+(1-G7)*G9 -> 0.07006405 | I10: 5 year Straight-line | J10: 1 | K10: =NPV(L82,$L$10:$Q$10)*L86 -> 0 | L10: 0.1 | M10: 0.2 | N10: 0.2 | O10: 0.2 | P10: 0.2 | Q10: 0.1
A11: WACC (real; after-tax) | B11: % | C11: =(1+C10)/(1+C6)-1 -> 0.043964926 | D11: =(1+D10)/(1+D6)-1 -> 0.026876134 | E11: =(1+E10)/(1+E6)-1 -> 0.061053719 | F11: =(1+F10)/(1+F6)-1 -> 0.043964926 | G11: =(1+G10)/(1+G6)-1 -> 0.043964926 | I11: 10 year Straight-line | J11: 1 | K11: =NPV(L82,$L$11:$V$11)*L86 -> 0 | L11: 0.05 | M11: 0.1 | N11: 0.1 | O11: 0.1 | P11: 0.1 | Q11: 0.1 | R11: 0.1 | S11: 0.1 | T11: 0.1 | U11: 0.1 | V11: 0.05
A12: Capital recovery factor (nominal; after-tax) | B12: % | C12: =(C10*(1+C10)^C2)/((1+C10)^C2-1) -> 0.085860035 | D12: =(D10*(1+D10)^D2)/((1+D10)^D2-1) -> 0.072775219 | E12: =(E10*(1+E10)^E2)/((1+E10)^E2-1) -> 0.099817026 | F12: =(F10*(1+F10)^F2)/((1+F10)^F2-1) -> 0.10983905 | G12: =(G10*(1+G10)^G2)/((1+G10)^G2-1) -> 0.077287913 | I12: 20 year Straight-line | J12: 1 | K12: =NPV(L82,$L$12:$AF$12)*L86 -> 0 | L12: 0.025 | M12: 0.05 | N12: 0.05 | O12: 0.05 | P12: 0.05 | Q12: 0.05 | R12: 0.05 | S12: 0.05 | T12: 0.05 | U12: 0.05 | V12: 0.05 | W12: 0.05 | X12: 0.05 | Y12: 0.05 | Z12: 0.05 | AA12: 0.05 | AB12: 0.05 | AC12: 0.05 | AD12: 0.05 | AE12: 0.05 | AF12: 0.025
A13: Capital recovery factor (real; after-tax) | B13: % | C13: =(C11*(1+C11)^C2)/((1+C11)^C2-1) -> 0.066722393 | D13: =(D11*(1+D11)^D2)/((1+D11)^D2-1) -> 0.055447426 | E13: =(E11*(1+E11)^E2)/((1+E11)^E2-1) -> 0.079011679 | F13: =(F11*(1+F11)^F2)/((1+F11)^F2-1) -> 0.092452403 | G13: =(G11*(1+G11)^G2)/((1+G11)^G2-1) -> 0.056496839 | I13: Depreciation Adjustment | K13: =IF(L87=I6,K6,IF(L77=I10,K10,IF(L77=I11,K11,IF(L77=I12,K12,"error")))) -> error
A14: Depreciable basis | B14: % | C14: 1 | D14: 1 | E14: 1 | F14: 1 | G14: 1 | I14: OpEx Schedule | L14: =L70 -> 0 | M14: =L14*(1+$AO$82) -> 0 | N14: =M14*(1+$AO$82) -> 0 | O14: =N14*(1+$AO$82) -> 0 | P14: =O14*(1+$AO$82) -> 0 | Q14: =P14*(1+$AO$82) -> 0 | R14: =Q14*(1+$AO$82) -> 0 | S14: =R14*(1+$AO$82) -> 0 | T14: =S14*(1+$AO$82) -> 0 | ... AE14: =AD14*(1+$AO$82) -> 0
A15: Depreciation schedule | C15: 5 year MACRS | D15: 5 year MACRS | E15: 5 year MACRS | F15: 5 year MACRS | G15: 5 year MACRS
A16: Depreciation adjustment (NPV) | B16: % | C16: =NPV(C$10,$L6:$Q6) -> 0.83141613 | D16: =NPV(D$10,$L6:$Q6) -> 0.86891345 | E16: =NPV(E$10,$L6:$Q6) -> 0.79653735 | F16: =NPV(F$10,$L6:$Q6) -> 0.83141613 | G16: =NPV(G$10,$L6:$Q6) -> 0.83141613
A17: Project finance factor | B17: % | C17: =(1-C3*C16)/(1-C3) -> 1.0583123 | D17: =(1-D3*D16)/(1-D3) -> 1.0453422 | E17: =(1-E3*E16)/(1-E3) -> 1.0703767 | F17: =(1-F3*F16)/(1-F3) -> 1.0583123 | G17: =(1-G3*G16)/(1-G3) -> 1.0583123
A18: FCR (nominal) | B18: % | C18: =C12*C17 -> 0.090866733 | D18: =D12*D17 -> 0.076075006 | E18: =E12*E17 -> 0.10684182 | F18: =F12*F17 -> 0.11624402 | G18: =G12*G17 -> 0.08179475
A19: FCR (real) | B19: % | C19: =C13*C17 -> 0.07061313 | D19: =D13*D17 -> 0.057961533 | E19: =E13*E17 -> 0.084572261 | F19: =F13*F17 -> 0.097843517 | G19: =G13*G17 -> 0.059791301
AD74: 20 | AE74: 25 | AF74: 30
AD75: 0.4 | AE75: 0.4 | AF75: 0.257
AD76: 0.35 | AE76: 0.35 | AF76: 0.21
AD77: 0.075 | AE77: 0.075 | AF77: 0.075
AD78: 0.025 | AE78: 0.025 | AF78: 0.025
AD79: 0.3 | AE79: 0.7 | AF79: 0.75
AD80: 0.037 | AE80: 0.037 | AF80: 0.045
AD81: 0.12 | AE81: 0.12 | AF81: 0.1
AD82: =AD79*(AD80*(1-AD75))+(1-AD79)*AD81 -> 0.09066 | AE82: =AE79*(AE80*(1-AE75))+(1-AE79)*AE81 -> 0.05154 | AF82: =AF79*(AF80*(1-AF75))+(1-AF79)*AF81 -> 0.05007625
AD83: =(1+AD82)/(1+AD78)-1 -> 0.064058537 | AE83: =(1+AE82)/(1+AE78)-1 -> 0.025892683 | AF83: =(1+AF82)/(1+AF78)-1 -> 0.024464634
AD84: =(AD82*(1+AD82)^AD74)/((1+AD82)^AD74-1) -> 0.11006217 | AE84: =(AE82*(1+AE82)^AE74)/((1+AE82)^AE74-1) -> 0.072051544 | AF84: =(AF82*(1+AF82)^AF74)/((1+AF82)^AF74-1) -> 0.065107988
AD85: =(AD83*(1+AD83)^AD74)/((1+AD83)^AD74-1) -> 0.090078842 | AE85: =(AE83*(1+AE83)^AE74)/((1+AE83)^AE74-1) -> 0.054831648 | AF85: =(AF83*(1+AF83)^AF74)/((1+AF83)^AF74-1) -> 0.047437243
AD86: 1 | AE86: 1 | AF86: 1
AD87: 5 year MACRS | AE87: 5 year MACRS | AF87: 5 year MACRS
AD88: =NPV(AD$82,$L6:$Q6) -> 0.7906567 | AE88: =NPV(AE$82,$L6:$Q6) -> 0.87115656 | AF88: =NPV(AF$82,$L6:$Q6) -> 0.87443086
AD89: =(1-AD75*AD88)/(1-AD75) -> 1.1395622 | AE89: =(1-AE75*AE88)/(1-AE75) -> 1.0858956 | AF89: =(1-AF75*AF88)/(1-AF75) -> 1.0434337
AD90: =AD84*AD89 -> 0.12542269 | AE90: =AE84*AE89 -> 0.078240456 | AF90: =AF84*AF89 -> 0.067935871
AD91: =AD85*AD89 -> 0.10265044 | AE91: =AE85*AE89 -> 0.059541446 | AF91: =AF85*AF89 -> 0.04949762
AD92: =(((AD39 * AD91) + AD70) / AD34 ) * 1000 -> #DIV/0! | AE92: =(((AE39 * AE91) + AE70) / AE34 ) * 1000 -> #DIV/0! | AF92: =(((AF39 * AF91) + AF70) / AF34 ) * 1000 -> #DIV/0!
